README.md
setup.py
barry_energy_api/__init__.py
barry_energy_api/utils.py
barry_energy_api.egg-info/PKG-INFO
barry_energy_api.egg-info/SOURCES.txt
barry_energy_api.egg-info/dependency_links.txt
barry_energy_api.egg-info/top_level.txt