Metadata-Version: 2.1
Name: barry-energy-api
Version: 1.0.0
Summary: Connecting to and getting data from Barry Energy's API (http://barry.energy)
Home-page: https://github.com/eelkjaer/BarryAPIClient
Author: Emil Elkjær Nielsen
Author-email: emil@evsn.dk
License: LICENS
Keywords: python barry energy api electricity prices barry.energy
Platform: UNKNOWN
Classifier: Development Status :: 4 - Beta
Classifier: Programming Language :: Python :: 3.9
Classifier: Topic :: Utilities
Classifier: License :: OSI Approved :: MIT License
